.gitignore
LICENSE
README.md
noxfile.py
requirements.test.txt
requirements.txt
setup.py
.github/workflows/publish.yaml
.github/workflows/tests.yaml
recruitment/__init__.py
recruitment.egg-info/PKG-INFO
recruitment.egg-info/SOURCES.txt
recruitment.egg-info/dependency_links.txt
recruitment.egg-info/requires.txt
recruitment.egg-info/top_level.txt
recruitment/agency/__init__.py
recruitment/agency/resources.py
recruitment/agency/temp.py
tests/__init__.py
tests/fixtures/s3.GetObject_1.json
tests/recruitment/__init__.py
tests/recruitment/agency/__init__.py
tests/recruitment/agency/test_agent.py
tests/recruitment/agency/test_broker.py
tests/recruitment/agency/test_commlink.py
tests/recruitment/agency/test_config.py
tests/recruitment/agency/test_consumer.py
tests/recruitment/agency/test_contingency.py
tests/recruitment/agency/test_job.py
tests/recruitment/agency/test_publisher.py