Metadata-Version: 2.1
Name: recruitment
Version: 0.8.2
Summary: a lib for sourcing actionpacked entities capable of getting the job done
Home-page: https://github.com/withtwoemms/recruitment
Author: Emmanuel I. Obi
Maintainer: Emmanuel I. Obi
Maintainer-email: withtwoemms@gmail.com
License: MIT
Platform: UNKNOWN
Classifier: Development Status :: 3 - Alpha
Classifier: Intended Audience :: Developers
Classifier: Intended Audience :: Education
Classifier: Intended Audience :: Science/Research
Classifier: Topic :: Software Development :: Build Tools
Classifier: License :: OSI Approved :: MIT License
Classifier: Programming Language :: Python :: 3.8
Classifier: Programming Language :: Python :: 3.9
Classifier: Programming Language :: Python :: 3.10
License-File: LICENSE
